netauto/__init__.py
netauto/_auth.py
netauto/_client.py
netauto/_cpe.py
netauto/_digi.py
netauto/_exceptions.py
netauto/_mac.py
netauto/_snmp.py
netauto/_tools.py
netauto/_validate.py
netauto/auth.py
netauto/digi.py
netauto/exceptions.py
netauto/mac.py
netauto/netauto.py
netauto/snmp.py
netauto/tools.py
netauto/models/__init__.py
netauto/models/cpe.py
netauto/models/digi.py
netauto/models/mac.py
netauto/models/snmp.py
netauto/models/tools.py
netauto-0.2.11.dist-info/METADATA
netauto-0.2.11.dist-info/WHEEL
netauto-0.2.11.dist-info/top_level.txt
netauto-0.2.11.dist-info/RECORD
