Metadata-Version: 2.1
Name: netauto
Version: 0.2.11
Summary: UNKNOWN
Home-page: UNKNOWN
Author: UNKNOWN
Author-email: UNKNOWN
License: UNKNOWN
Platform: UNKNOWN
Requires-Dist: httpx (==0.13.3)
Requires-Dist: pydantic (==1.5)
